beta_batch_encoder/__init__.py
beta_batch_encoder/__main__.py
beta_batch_encoder/_bitrate_mode.py
beta_batch_encoder/_colorspace.py
beta_batch_encoder/_encode_webm.py
beta_batch_encoder/_encoding_config.py
beta_batch_encoder/_interface.py
beta_batch_encoder/_loudnorm_filter.py
beta_batch_encoder/_seek.py
beta_batch_encoder/_seek_collector.py
beta_batch_encoder/_source_file.py
beta_batch_encoder/_utils.py
animethemes_beta_batch_encoder-1.4.1.dist-info/LICENSE
animethemes_beta_batch_encoder-1.4.1.dist-info/METADATA
animethemes_beta_batch_encoder-1.4.1.dist-info/WHEEL
animethemes_beta_batch_encoder-1.4.1.dist-info/top_level.txt
animethemes_beta_batch_encoder-1.4.1.dist-info/RECORD
